charitycommissionew/__init__.py
charitycommissionew/charitycommissionew.py
charitycommissionew-0.1.1.dist-info/LICENSE
charitycommissionew-0.1.1.dist-info/METADATA
charitycommissionew-0.1.1.dist-info/WHEEL
charitycommissionew-0.1.1.dist-info/top_level.txt
charitycommissionew-0.1.1.dist-info/RECORD
