Metadata-Version: 2.1
Name: charitycommissionew
Version: 0.1.1
Summary: Charity Commission England and Wales - Data Library
Home-page: UNKNOWN
Author: Callum Robson-Port
Author-email: 
License: MIT
Platform: UNKNOWN
Classifier: Intended Audience :: Developers
Classifier: License :: OSI Approved :: MIT License
Classifier: Programming Language :: Python
Classifier: Programming Language :: Python :: 3
Classifier: Programming Language :: Python :: 3.6
Classifier: Programming Language :: Python :: 3.7
Classifier: Programming Language :: Python :: 3.8
Classifier: Programming Language :: Python :: 3.9
Classifier: Operating System :: OS Independent
Requires-Dist: validators
